{
  "url": "http://nazrulmuhaimin.com",
  "server": {
    "port": 2368,
    "host": "127.0.0.1"
  },
  "database": {
    "client": "mysql",
    "connection": {
      "host": "localhost",
      "user": "ghost-760",
      "password": "bml3oEKC*l2hJY]}t$$$",
      "database": "juggernaz"
    }
  },
  "mail": {
    "transport": "Direct"
  },
  "logging": {
    "transports": [
      "file",
      "stdout"
    ]
  },
  "process": "systemd",
  "paths": {
    "contentPath": "/var/www/ghost/content"
  }
}
